<annotation>
	<folder>train</folder>
	<filename>frame505.jpg</filename>
	<path>D:\programming\python\CYBERRYBA\images-tf\train\frame505.jpg</path>
	<source>
		<database>Unknown</database>
	</source>
	<size>
		<width>640</width>
		<height>400</height>
		<depth>3</depth>
	</size>
	<segmented>0</segmented>
	<object>
		<name>black</name>
		<pose>Unspecified</pose>
		<truncated>0</truncated>
		<difficult>0</difficult>
		<bndbox>
			<xmin>399</xmin>
			<ymin>196</ymin>
			<xmax>448</xmax>
			<ymax>291</ymax>
		</bndbox>
	</object>
</annotation>
